pasha/__init__.py
pasha/context.py
pasha/functor.py
pasha-0.1.2.dist-info/LICENSE
pasha-0.1.2.dist-info/METADATA
pasha-0.1.2.dist-info/WHEEL
pasha-0.1.2.dist-info/top_level.txt
pasha-0.1.2.dist-info/RECORD
