Metadata-Version: 2.1
Name: pasha
Version: 0.1.2
Summary: Tools to parallelize operations on large data sets using shared memory with zero copies.
Home-page: https://github.com/European-XFEL/pasha
Author: Philipp Schmidt
Author-email: philipp.schmidt@xfel.eu
License: BSD-3-Clause
Classifier: Development Status :: 3 - Alpha
Classifier: Intended Audience :: Developers
Classifier: Intended Audience :: Science/Research
Classifier: License :: OSI Approved :: BSD License
Classifier: Operating System :: POSIX :: Linux
Classifier: Topic :: Scientific/Engineering :: Information Analysis
Classifier: Topic :: Scientific/Engineering :: Physics
Requires-Python: >=3.6
License-File: LICENSE
Requires-Dist: numpy
Provides-Extra: test
Requires-Dist: pytest; extra == "test"
Requires-Dist: xarray; extra == "test"
